tradepunk/__init__.py
tradepunk-0.0.1.dist-info/METADATA
tradepunk-0.0.1.dist-info/WHEEL
tradepunk-0.0.1.dist-info/licenses/LICENSE
tradepunk-0.0.1.dist-info/RECORD
